feng_big-0.0.2.dist-info/myfile/bert_model.ckpt.meta
hanlingzhi/__init__.py
hanlingzhi/math_h.py
string_h/__init__.py
string_h/reverse.py
feng_big-0.0.2.dist-info/LICENSE.txt
feng_big-0.0.2.dist-info/METADATA
feng_big-0.0.2.dist-info/WHEEL
feng_big-0.0.2.dist-info/top_level.txt
feng_big-0.0.2.dist-info/RECORD
