Metadata-Version: 2.1
Name: feng-big
Version: 0.0.2
Summary: 验证打包功能的测试包, 请勿下载
Author: heyang
Author-email: hey505442@gmail.com
License: MIT
Keywords: hanlingzhi package demo
Classifier: Development Status :: 3 - Alpha
Classifier: Intended Audience :: Developers
Classifier: Topic :: Software Development :: Build Tools
Classifier: License :: OSI Approved :: MIT License
Classifier: Programming Language :: Python :: 3
Classifier: Programming Language :: Python :: 3.2
Classifier: Programming Language :: Python :: 3.3
Classifier: Programming Language :: Python :: 3.4
Classifier: Operating System :: OS Independent
Requires-Python: >=3.6
License-File: LICENSE.txt
Requires-Dist: pytest
